{
  "@context": "http://iiif.io/api/presentation/2/context.json",
  "@id": "annotations/article6",
  "@type": "sc:AnnotationList",
  "label": "ROSS BOURGER FRIDAY EVENING TO BE FORMAL",
  "resources": [
    {
      "@id": "ocrFile1-P1_TB00023",
      "@type": [
        "oa:Annotation",
        "umd:Article"
      ],
      "resource": [
        {
          "@type": "cnt:ContentAsText",
          "format": "text/plain",
          "chars": "ROSS BOURGER FRIDAY\nEVENING TO BE FORMAL\n"
        }
      ],
      "on": {
        "@type": "oa:SpecificResource",
        "selector": {
          "@type": "oa:FragmentSelector",
          "value": "xywh=2589,3836,712,161"
        },
        "full": "pageFileGrp1"
      },
      "motivation": "oa:highlighting"
    },
    {
      "@id": "ocrFile1-P1_TB00024",
      "@type": [
        "oa:Annotation",
        "umd:Article"
      ],
      "resource": [
        {
          "@type": "cnt:ContentAsText",
          "format": "text/plain",
          "chars": "Friday night and Ritchie gym-\nnasium will find the Rossbourg\nClub and Its guests participating in\nthe first formal dance of the year.\nThe hop was promised by the club\nofficials sometime before Christ-\nmas, and every possible moans will\nbe employed to present one of the\nmost succssful dances of the season.\nBob lula in person with a six\npiece orchestra will furnish the\nmusic for the affair. Bob will tune\nup about 10 o’clock and play on un-\ntil 1 a. m., at which time the Ross-\nbourgers will cease to make merry.\nOf course the musicians will be in-\nterrupted while the usual refresh-\nments are being consumed.\nAn assessment of $2 will be\ncharged non-members of the club,\nwhile stags are requested to bring\n$1.50 along if they wish to gain ad-\nmission.\nThe dance is the third for the\nclub which means that only two\nmore remain on the schedule.\n- U. of M. \n"
        }
      ],
      "on": {
        "@type": "oa:SpecificResource",
        "selector": {
          "@type": "oa:FragmentSelector",
          "value": "xywh=2587,4066,713,1346"
        },
        "full": "pageFileGrp1"
      },
      "motivation": "oa:highlighting"
    }
  ]
}
